bangpg/__init__.py
bangpg-0.1.1.dist-info/METADATA
bangpg-0.1.1.dist-info/WHEEL
bangpg-0.1.1.dist-info/top_level.txt
bangpg-0.1.1.dist-info/RECORD
