Metadata-Version: 2.1
Name: bangpg
Version: 0.1.1
Summary: This packeges implements a faster alternative `to_sql()` method for PostgreSQL that support COPY FROM.
Home-page: https://github.com/matheus0sa/bangpg
Author: MATHEUS DE SA DE SOUZA
Author-email: matheusdesa55@gmail.com
Classifier: Programming Language :: Python :: 3
Classifier: License :: OSI Approved :: MIT License
Classifier: Operating System :: OS Independent
Requires-Python: >=3.6
